curlrc.py
curlrc-0.2.0.dist-info/DESCRIPTION.rst
curlrc-0.2.0.dist-info/entry_points.txt
curlrc-0.2.0.dist-info/METADATA
curlrc-0.2.0.dist-info/metadata.json
curlrc-0.2.0.dist-info/RECORD
curlrc-0.2.0.dist-info/top_level.txt
curlrc-0.2.0.dist-info/WHEEL
