Metadata-Version: 2.0
Name: curlrc
Version: 0.2.0
Summary: Treat curl configuration files as curlrc subcommands.
Home-page: https://github.com/benwebber/curlrc/
Author: Ben Webber
Author-email: benjamin.webber@gmail.com
License: UNKNOWN
Platform: UNKNOWN
Classifier: Development Status :: 4 - Beta
Classifier: Programming Language :: Python :: 2
Classifier: Programming Language :: Python :: 2.7
Classifier: Programming Language :: Python :: 3
Classifier: Programming Language :: Python :: 3.4
Classifier: Programming Language :: Python :: 3.5
